{
	"description": "项目配置文件。",
	"packOptions": {
		"ignore": []
	},
	"setting": {
		"urlCheck": false,
		"es6": true,
		"postcss": true,
		"minified": true,
		"newFeature": true,
		"coverView": true,
		"autoAudits": false,
		"showShadowRootInWxmlPanel": true,
		"scopeDataCheck": false,
		"checkInvalidKey": true,
		"checkSiteMap": true,
		"uploadWithSourceMap": true,
		"babelSetting": {
			"ignore": [],
			"disablePlugins": [],
			"outputPath": ""
		}
	},
	"compileType": "miniprogram",
	"libVersion": "1.9.98",
	"appid": "wx993172f7da9acf1f",
	"projectname": "video",
	"isGameTourist": false,
	"simulatorType": "wechat",
	"simulatorPluginLibVersion": {},
	"condition": {
		"search": {
			"current": -1,
			"list": []
		},
		"conversation": {
			"current": -1,
			"list": []
		},
		"plugin": {
			"current": -1,
			"list": []
		},
		"game": {
			"currentL": -1,
			"list": []
		},
		"gamePlugin": {
			"current": -1,
			"list": []
		},
		"miniprogram": {
			"current": -1,
			"list": [
				{
					"id": 0,
					"name": "登陆",
					"pathName": "pages/userLogin/login",
					"query": "",
					"scene": null
				},
				{
					"id": 1,
					"name": "注册",
					"pathName": "pages/userRegist/regist",
					"query": "",
					"scene": null
				},
				{
					"id": 2,
					"name": "个人首页",
					"pathName": "pages/mine/mine",
					"query": "",
					"scene": null
				},
				{
					"id": -1,
					"name": "上传音乐",
					"pathName": "pages/chooseBgm/chooseBgm",
					"query": "",
					"scene": null
				},
				{
					"id": -1,
					"name": "首页",
					"pathName": "pages/index/index",
					"query": "",
					"scene": null
				},
				{
					"id": -1,
					"name": "搜索",
					"pathName": "pages/searchVideo/searchVideo",
					"query": "",
					"scene": null
				},
				{
					"id": -1,
					"name": "举报",
					"pathName": "pages/report/report",
					"scene": null
				}
			]
		}
	}
}